LICENSE
MANIFEST.in
README.rst
setup.py
goto/__init__.py
goto/goto.py
goto/useragents.py
goto/utils.py
goto.egg-info/PKG-INFO
goto.egg-info/SOURCES.txt
goto.egg-info/dependency_links.txt
goto.egg-info/top_level.txt