Metadata-Version: 1.0
Name: goto
Version: 0.0.1
Summary: Urllib object wrapper
Home-page: https://bitbucket.org/imbolc/goto
Author: Imbolc
Author-email: imbolc@imbolc.name
License: ISC
Platform: UNKNOWN
Classifier: Development Status :: 4 - Beta
Classifier: Intended Audience :: Developers
Classifier: Natural Language :: English
Classifier: License :: OSI Approved :: ISC License (ISCL)
Classifier: Programming Language :: Python
